README.md
setup.py
xmlrpclib_to/__init__.py
xmlrpclib_to.egg-info/PKG-INFO
xmlrpclib_to.egg-info/SOURCES.txt
xmlrpclib_to.egg-info/dependency_links.txt
xmlrpclib_to.egg-info/top_level.txt