Metadata-Version: 1.0
Name: xmlrpclib-to
Version: 0.1.2
Summary: XMLRPC Client with timeout
Home-page: http://github.com/gisce/xmlrpclib-to
Author: GISCE-TI, S.L.
Author-email: devel@gisce.net
License: MIT
Platform: UNKNOWN
